class_argparse/__init__.py
class_argparse-0.1.4.dist-info/licenses/LICENSE
class_argparse-0.1.4.dist-info/METADATA
class_argparse-0.1.4.dist-info/WHEEL
class_argparse-0.1.4.dist-info/top_level.txt
class_argparse-0.1.4.dist-info/RECORD
