Metadata-Version: 2.4
Name: class-argparse
Version: 0.1.4
Summary: Class based argument parser
Home-page: https://github.com/neblar/class-argparse
Author: Neblar
Author-email: support@neblar.com
License: MIT
Keywords: Class Based,CLI,Argparse
Classifier: Development Status :: 4 - Beta
Classifier: Intended Audience :: Developers
Classifier: License :: OSI Approved :: MIT License
Classifier: Operating System :: OS Independent
Classifier: Topic :: Utilities
License-File: LICENSE
Dynamic: author
Dynamic: author-email
Dynamic: classifier
Dynamic: description
Dynamic: description-content-type
Dynamic: home-page
Dynamic: keywords
Dynamic: license
Dynamic: license-file
Dynamic: summary
